example/__init__.py
example/hn_motor.py
ruia_motor/__init__.py
ruia_motor/motor_base.py
ruia_motor-0.0.5.dist-info/LICENSE
ruia_motor-0.0.5.dist-info/METADATA
ruia_motor-0.0.5.dist-info/WHEEL
ruia_motor-0.0.5.dist-info/top_level.txt
ruia_motor-0.0.5.dist-info/RECORD
