Metadata-Version: 2.1
Name: ruia-motor
Version: 0.0.5
Summary: ruia_motor - a Ruia plugin that uses the motor to store data
Home-page: https://github.com/python-ruia/ruia-motor
Author: Howie Hu
Author-email: xiaozizayang@gmail.com
License: MIT
Project-URL: Documentation, https://github.com/python-ruia/ruia-motor
Project-URL: Source, https://github.com/python-ruia/ruia-motor
Platform: UNKNOWN
Classifier: Intended Audience :: Developers
Classifier: License :: OSI Approved :: MIT License
Classifier: Programming Language :: Python :: 3.6
Classifier: Programming Language :: Python :: 3.7
Classifier: Programming Language :: Python :: 3.8
Classifier: Programming Language :: Python :: 3.9
Classifier: Topic :: Software Development :: Libraries :: Python Modules
License-File: LICENSE
Requires-Dist: motor
Requires-Dist: ruia (>=0.8.0)
